README.rst
setup.py
cjutools/__init__.py
cjutools/__main__.py
cjutools.egg-info/PKG-INFO
cjutools.egg-info/SOURCES.txt
cjutools.egg-info/dependency_links.txt
cjutools.egg-info/requires.txt
cjutools.egg-info/top_level.txt
cjutools/cmds/__init__.py
cjutools/cmds/format_ext.py