Metadata-Version: 2.1
Name: cjutools
Version: 0.0.9
Summary: tools depend cjutils
Home-page: https://github.com/CJYLZS/cjtools.git
Author: cjylzs
Author-email: 691086891@qq.com
License: MIT License
Keywords: cjutools
Platform: any
